flight_ad/__init__.py
flight_ad/cluster/__init__.py
flight_ad/cluster/_dbscan.py
flight_ad/datasets/__init__.py
flight_ad/datasets/_interface.py
flight_ad/datasets/dashlink.py
flight_ad/datasets/data.json
flight_ad/learn/__init__.py
flight_ad/learn/function_estimator.py
flight_ad/learn/stats_learner.py
flight_ad/math/__init__.py
flight_ad/math/geometry.py
flight_ad/pipeline/__init__.py
flight_ad/pipeline/ad.py
flight_ad/reconstruction/__init__.py
flight_ad/reconstruction/_autoencoder.py
flight_ad/report/__init__.py
flight_ad/report/cluster.py
flight_ad/transformations/__init__.py
flight_ad/transformations/transforms.py
flight_ad/utils/__init__.py
flight_ad/utils/_sklearn_interface.py
flight_ad/utils/data/__init__.py
flight_ad/utils/data/interface.py
flight_ad/viz/__init__.py
flight_ad/viz/chart.py
flight_ad/wrangling/__init__.py
flight_ad/wrangling/operations.py
flight_ad/wrangling/wrangler.py
flight_ad-0.0.1.dist-info/LICENSE
flight_ad-0.0.1.dist-info/METADATA
flight_ad-0.0.1.dist-info/WHEEL
flight_ad-0.0.1.dist-info/top_level.txt
flight_ad-0.0.1.dist-info/RECORD
