Metadata-Version: 2.1
Name: flight-ad
Version: 0.0.1
Summary: flight-ad is a Python package for anomaly detection in the aviation domain built on top of scikit-learn.
Home-page: https://github.com/coelhosilva/flight-ad.git
Author: Lucas Coelho e Silva
License: MIT
Download-URL: https://github.com/coelhosilva/flight-ad/archive/refs/tags/v0.0.1.tar.gz
Platform: UNKNOWN
Classifier: License :: OSI Approved :: MIT License
Classifier: Programming Language :: Python
Classifier: Programming Language :: Python :: 3
Classifier: Programming Language :: Python :: 3 :: Only
Classifier: Programming Language :: Python :: 3.8
Classifier: Programming Language :: Python :: 3.9
Classifier: Operating System :: OS Independent
Classifier: Topic :: Scientific/Engineering
Classifier: Topic :: Scientific/Engineering :: Artificial Intelligence
Requires-Python: >=3.8
License-File: LICENSE
Requires-Dist: numpy (~=1.20.3)
Requires-Dist: scikit-learn (~=0.24.2)
Requires-Dist: pandas (~=1.2.4)
Requires-Dist: matplotlib (~=3.4.2)
Requires-Dist: pyarrow (~=4.0.1)
Requires-Dist: tqdm (~=4.61.1)
